robocorp/log_pytest/__init__.py
robocorp_log_pytest-0.0.5.dist-info/METADATA
robocorp_log_pytest-0.0.5.dist-info/WHEEL
robocorp_log_pytest-0.0.5.dist-info/entry_points.txt
robocorp_log_pytest-0.0.5.dist-info/RECORD
