Metadata-Version: 2.3
Name: robocorp-log-pytest
Version: 0.0.5
Summary: PyTest plugin for auto-logging of pytest tests with robocorp-log.
License: Apache-2.0
Author: Fabio Zadrozny
Author-email: fabio@robocorp.com
Requires-Python: >=3.9.2,<4.0.0
Classifier: Development Status :: 4 - Beta
Classifier: Framework :: Pytest
Classifier: License :: OSI Approved :: Apache Software License
Classifier: Programming Language :: Python :: 3
Classifier: Programming Language :: Python :: 3.10
Classifier: Programming Language :: Python :: 3.11
Classifier: Programming Language :: Python :: 3.12
Classifier: Programming Language :: Python :: 3.13
Classifier: Programming Language :: Python :: 3.9
Classifier: Topic :: Software Development :: Libraries :: Python Modules
Classifier: Topic :: System :: Logging
Requires-Dist: pytest (>=7)
Requires-Dist: robocorp-log (>=2.5,<4)
Project-URL: Repository, https://github.com/robocorp/robocorp/
